YuehuiJinshu/README.md
YuehuiJinshu/__init__.py
YuehuiJinshu/__main__.py
YuehuiJinshu/file.epub
YuehuiJinshu/index.html
YuehuiJinshu/css/__init__.py
YuehuiJinshu/css/annotations.css
YuehuiJinshu/css/main.css
YuehuiJinshu/css/normalize.css
YuehuiJinshu/css/popup.css
YuehuiJinshu/font/__init__.py
YuehuiJinshu/font/fontello.eot
YuehuiJinshu/font/fontello.svg
YuehuiJinshu/font/fontello.ttf
YuehuiJinshu/font/fontello.woff
YuehuiJinshu/img/__init__.py
YuehuiJinshu/img/annotator-glyph-sprite.png
YuehuiJinshu/img/annotator-icon-sprite.png
YuehuiJinshu/img/apple-touch-icon.png
YuehuiJinshu/img/cancelfullscreen.png
YuehuiJinshu/img/close.png
YuehuiJinshu/img/fullscreen.png
YuehuiJinshu/img/loader.gif
YuehuiJinshu/img/menu-icon.png
YuehuiJinshu/img/save.png
YuehuiJinshu/img/saved.png
YuehuiJinshu/img/settings-s.png
YuehuiJinshu/img/settings.png
YuehuiJinshu/img/star.png
YuehuiJinshu/js/__init__.py
YuehuiJinshu/js/epub.js
YuehuiJinshu/js/epub.min.js
YuehuiJinshu/js/epub.min.map
YuehuiJinshu/js/hooks.min.js
YuehuiJinshu/js/hooks.min.map
YuehuiJinshu/js/reader.js
YuehuiJinshu/js/reader.js.map
YuehuiJinshu/js/reader.min.js
YuehuiJinshu/js/reader.min.map
YuehuiJinshu/js/hooks/__init__.py
YuehuiJinshu/js/hooks/extensions/__init__.py
YuehuiJinshu/js/hooks/extensions/highlight.js
YuehuiJinshu/js/libs/__init__.py
YuehuiJinshu/js/libs/jquery.min.js
YuehuiJinshu/js/libs/localforage.min.js
YuehuiJinshu/js/libs/screenfull.js
YuehuiJinshu/js/libs/screenfull.min.js
YuehuiJinshu/js/libs/zip.min.js
YuehuiJinshu/js/plugins/__init__.py
YuehuiJinshu/js/plugins/hypothesis.js
YuehuiJinshu/js/plugins/search.js
yuehui_jinshu-2022.10.11.0.dist-info/METADATA
yuehui_jinshu-2022.10.11.0.dist-info/WHEEL
yuehui_jinshu-2022.10.11.0.dist-info/entry_points.txt
yuehui_jinshu-2022.10.11.0.dist-info/top_level.txt
yuehui_jinshu-2022.10.11.0.dist-info/RECORD
